ot_arhmm/__init__.py
ot_arhmm/switching.py
ot_arhmm-0.3.1.dist-info/METADATA
ot_arhmm-0.3.1.dist-info/WHEEL
ot_arhmm-0.3.1.dist-info/licenses/LICENSE
ot_arhmm-0.3.1.dist-info/RECORD
